.gitignore
MANIFEST.in
README.md
requirements.txt
setup.py
gclouddatastore/.dataset.py.swp
gclouddatastore/.key_test.py.swp
gclouddatastore/.test_dataset.py.swp
gclouddatastore/__init__.py
gclouddatastore/connection.py
gclouddatastore/credentials.py
gclouddatastore/dataset.py
gclouddatastore/datastore_v1_pb2.py
gclouddatastore/entity.py
gclouddatastore/helpers.py
gclouddatastore/key.py
gclouddatastore/query.py
gclouddatastore/test_dataset.py
gclouddatastore/test_entity.py
gclouddatastore/test_key.py
gclouddatastore/transaction.py
gclouddatastore.egg-info/PKG-INFO
gclouddatastore.egg-info/SOURCES.txt
gclouddatastore.egg-info/dependency_links.txt
gclouddatastore.egg-info/requires.txt
gclouddatastore.egg-info/top_level.txt
gclouddatastore/demo/__init__.py
gclouddatastore/demo/demo.py
gclouddatastore/demo/jgatsby-storage.key