Metadata-Version: 1.1
Name: gclouddatastore
Version: 0.1.2
Summary: API Client library for Google Cloud Datastore
Home-page: https://github.com/jgeewax/gclouddatastore
Author: JJ Geewax
Author-email: jj@geewax.org
License: Apache 2.0
Platform: Posix; MacOS X; Windows
Classifier: Development Status :: 3 - Alpha
Classifier: Intended Audience :: Developers
Classifier: License :: OSI Approved :: Apache Software License
Classifier: Operating System :: OS Independent
Classifier: Programming Language :: Python :: 2
Classifier: Programming Language :: Python :: 2.5
Classifier: Programming Language :: Python :: 2.6
Classifier: Programming Language :: Python :: 2.7
Classifier: Topic :: Internet
